requests/__init__.py
requests/__version__.py
requests/_internal_utils.py
requests/adapters.py
requests/api.py
requests/auth.py
requests/certs.py
requests/compat.py
requests/cookies.py
requests/exceptions.py
requests/help.py
requests/hooks.py
requests/models.py
requests/packages.py
requests/sessions.py
requests/status_codes.py
requests/structures.py
requests/utils.py
requests_freeproxy/__init__.py
requests_freeproxy/__version__.py
requests_freeproxy/_internal_utils.py
requests_freeproxy/adapters.py
requests_freeproxy/api.py
requests_freeproxy/auth.py
requests_freeproxy/certs.py
requests_freeproxy/compat.py
requests_freeproxy/cookies.py
requests_freeproxy/exceptions.py
requests_freeproxy/help.py
requests_freeproxy/hooks.py
requests_freeproxy/models.py
requests_freeproxy/packages.py
requests_freeproxy/sessions.py
requests_freeproxy/status_codes.py
requests_freeproxy/structures.py
requests_freeproxy/utils.py
requestsproxy/__init__.py
requestsproxy/__version__.py
requestsproxy/_internal_utils.py
requestsproxy/adapters.py
requestsproxy/api.py
requestsproxy/auth.py
requestsproxy/certs.py
requestsproxy/compat.py
requestsproxy/cookies.py
requestsproxy/exceptions.py
requestsproxy/help.py
requestsproxy/hooks.py
requestsproxy/models.py
requestsproxy/packages.py
requestsproxy/sessions.py
requestsproxy/status_codes.py
requestsproxy/structures.py
requestsproxy/utils.py
requests_freeproxy-2.31.0.dist-info/LICENSE
requests_freeproxy-2.31.0.dist-info/METADATA
requests_freeproxy-2.31.0.dist-info/WHEEL
requests_freeproxy-2.31.0.dist-info/top_level.txt
requests_freeproxy-2.31.0.dist-info/RECORD
